nonebot_plugin_vocu/__init__.py
nonebot_plugin_vocu/config.py
nonebot_plugin_vocu/matcher.py
nonebot_plugin_vocu/vocu.py
nonebot_plugin_template-0.1.0.dist-info/LICENSE
nonebot_plugin_template-0.1.0.dist-info/METADATA
nonebot_plugin_template-0.1.0.dist-info/WHEEL
nonebot_plugin_template-0.1.0.dist-info/top_level.txt
nonebot_plugin_template-0.1.0.dist-info/RECORD
