Metadata-Version: 2.2
Name: nonebot-plugin-template
Version: 0.1.0
Summary: 插件描述
Author-email: fllesser <fllessive@gmail.com>
Requires-Python: <3.13,>=3.10
License-File: LICENSE
Requires-Dist: httpx<1.0.0,>=0.27.0
Requires-Dist: nonebot2<3.0.0,>=2.4.0
Requires-Dist: nonebot-adapter-onebot<3.0.0,>=2.4.6
